{
  "$schema": "https://mintlify.com/docs.json",
  "name": "Gobarau Academy Backend",
  "theme": "luma",
  "colors": {
    "primary": "#1B6B3A",
    "light": "#E6F4EC",
    "dark": "#0D3D20"
  },
  "navbar": {
    "primary": {
      "type": "github",
      "href": "https://github.com/muhammadbugaje/gobarau_backend"
    }
  },
  "footer": {
    "socials": {
      "github": "https://github.com/muhammadbugaje/gobarau_backend"
    }
  },
  "navigation": {
    "tabs": [
      {
        "tab": "Documentation",
        "groups": [
          {
            "group": "Get Started",
            "pages": [
              "introduction",
              "quickstart",
              "authentication"
            ]
          },
          {
            "group": "Core Concepts",
            "pages": [
              "concepts/architecture",
              "concepts/roles-and-permissions",
              "concepts/data-model"
            ]
          },
          {
            "group": "Guides",
            "pages": [
              "guides/setup",
              "guides/deployment",
              "guides/configuration"
            ]
          }
        ]
      },
      {
        "tab": "API Reference",
        "groups": [
          {
            "group": "Administration",
            "pages": [
              "api/administration",
              "api/accounts"
            ]
          },
          {
            "group": "People & Admissions",
            "pages": [
              "api/people",
              "api/admissions"
            ]
          },
          {
            "group": "Academics",
            "pages": [
              "api/academics",
              "api/welfare"
            ]
          },
          {
            "group": "Finance & Services",
            "pages": [
              "api/finance",
              "api/services"
            ]
          },
          {
            "group": "Communication & Content",
            "pages": [
              "api/communication",
              "api/content"
            ]
          }
        ]
      }
    ]
  }
}
